README.md
setup.py
webdriver_assistant/__init__.py
webdriver_assistant.egg-info/PKG-INFO
webdriver_assistant.egg-info/SOURCES.txt
webdriver_assistant.egg-info/dependency_links.txt
webdriver_assistant.egg-info/top_level.txt