Metadata-Version: 1.0
Name: webdriver-assistant
Version: 0.0.3
Summary: webdriver assistant
Home-page: https://github.com/ytyng/python-webdriver-assistant
Author: ytyng
Author-email: ytyng@live.jp
License: UNKNOWN
Platform: UNKNOWN
